pydif/__init__.py
pydif/app.py
pydif/main.py
pydif/config/__init__.py
pydif/config/py_validator_config.cfg
pydif/config/py_validator_setup.csv
pydif/exception/__init__.py
pydif/exception/customExceptions.py
pydif/lib/__init__.py
pydif/lib/create_directory.py
pydif/lib/py_validator_lib.py
spydif-0.4.dist-info/LICENSE.txt
spydif-0.4.dist-info/METADATA
spydif-0.4.dist-info/WHEEL
spydif-0.4.dist-info/entry_points.txt
spydif-0.4.dist-info/top_level.txt
spydif-0.4.dist-info/RECORD
